botleague_helpers/__init__.py
botleague_helpers/config.py
botleague_helpers/constants.py
botleague_helpers/db.py
botleague_helpers/key_value_store.py
botleague_helpers/mockable.py
botleague_helpers/test_live_db.py
botleague_helpers-0.1.0.dist-info/LICENSE.md
botleague_helpers-0.1.0.dist-info/METADATA
botleague_helpers-0.1.0.dist-info/WHEEL
botleague_helpers-0.1.0.dist-info/top_level.txt
botleague_helpers-0.1.0.dist-info/zip-safe
botleague_helpers-0.1.0.dist-info/RECORD
